secureshare/__init__.py
secureshare/cli.py
z_secshare-0.1.0.dist-info/METADATA
z_secshare-0.1.0.dist-info/WHEEL
z_secshare-0.1.0.dist-info/top_level.txt
z_secshare-0.1.0.dist-info/RECORD
