Metadata-Version: 2.4
Name: z-secshare
Version: 0.1.0
Summary: CLI encrypted file sharing tool
Author-email: Zero <your-email@example.com>
Requires-Python: >=3.8
Requires-Dist: cryptography>=40.0
